init_file_checker.py
init_file_checker-0.0.2.dist-info/LICENSE
init_file_checker-0.0.2.dist-info/METADATA
init_file_checker-0.0.2.dist-info/WHEEL
init_file_checker-0.0.2.dist-info/entry_points.txt
init_file_checker-0.0.2.dist-info/RECORD
