Metadata-Version: 2.1
Name: init-file-checker
Version: 0.0.2
Summary: Checker of __init__.py files in Python projects
Home-page: https://github.com/DavidPal/init-file-checker
License: MIT
Author: David Pal
Author-email: davidko.pal@gmail.com
Requires-Python: >=3.8.5,<4.0.0
Classifier: License :: OSI Approved :: MIT License
Classifier: Programming Language :: Python
Classifier: Programming Language :: Python :: 3
Classifier: Programming Language :: Python :: 3.9
Classifier: Programming Language :: Python :: 3.10
Classifier: Programming Language :: Python :: 3.11
Classifier: Programming Language :: Python :: 3.12
Project-URL: Repository, https://github.com/DavidPal/init-file-checker
